honeybee_grasshopper_radiance/__init__.py
honeybee_grasshopper_radiance/src/HB Adjust HDR.py
honeybee_grasshopper_radiance/src/HB Ambient Resolution.py
honeybee_grasshopper_radiance/src/HB Annual Average Values.py
honeybee_grasshopper_radiance/src/HB Annual Cumulative Values.py
honeybee_grasshopper_radiance/src/HB Annual Daylight Metrics.py
honeybee_grasshopper_radiance/src/HB Annual Daylight.py
honeybee_grasshopper_radiance/src/HB Annual Glare Metrics.py
honeybee_grasshopper_radiance/src/HB Annual Irradiance.py
honeybee_grasshopper_radiance/src/HB Annual Peak Values.py
honeybee_grasshopper_radiance/src/HB Annual Results to Data.py
honeybee_grasshopper_radiance/src/HB Annual Statistics.py
honeybee_grasshopper_radiance/src/HB Annual Sunlight Exposure.py
honeybee_grasshopper_radiance/src/HB Aperture Group Schedule.py
honeybee_grasshopper_radiance/src/HB Apply Face Modifier.py
honeybee_grasshopper_radiance/src/HB Apply ModifierSet.py
honeybee_grasshopper_radiance/src/HB Apply Shade Modifier.py
honeybee_grasshopper_radiance/src/HB Apply Window Modifier.py
honeybee_grasshopper_radiance/src/HB Assign Grids and Views.py
honeybee_grasshopper_radiance/src/HB Automatic Aperture Group.py
honeybee_grasshopper_radiance/src/HB BSDF Modifier.py
honeybee_grasshopper_radiance/src/HB CIE Standard Sky.py
honeybee_grasshopper_radiance/src/HB Certain Illuminance.py
honeybee_grasshopper_radiance/src/HB Check Scene.py
honeybee_grasshopper_radiance/src/HB Climatebased Sky.py
honeybee_grasshopper_radiance/src/HB Cumulative Radiation.py
honeybee_grasshopper_radiance/src/HB Custom Sky.py
honeybee_grasshopper_radiance/src/HB Daylight Control Schedule.py
honeybee_grasshopper_radiance/src/HB Daylight Factor.py
honeybee_grasshopper_radiance/src/HB Deconstruct Modifier.py
honeybee_grasshopper_radiance/src/HB Deconstruct ModifierSet Interior.py
honeybee_grasshopper_radiance/src/HB Deconstruct ModifierSet.py
honeybee_grasshopper_radiance/src/HB Deconstruct Wea.py
honeybee_grasshopper_radiance-1.35.5.dist-info/licenses/LICENSE
honeybee_grasshopper_radiance-1.35.5.dist-info/METADATA
honeybee_grasshopper_radiance-1.35.5.dist-info/WHEEL
honeybee_grasshopper_radiance-1.35.5.dist-info/top_level.txt
honeybee_grasshopper_radiance-1.35.5.dist-info/RECORD
